{
  "Index": {
    "name": "Simon Achkar",
    "title": "Développeur de Logiciels Senior chez <a href='https://www.redspace.com/' target='_blank' rel='noreferrer'>REDspace</a>",
    "tag": "Je construis des solutions digitales pour le web",
    "downloadResume": "Télécharger mon CV",
    "aboutText": "Je suis un développeur Full-Stack avec plus de 6 ans d'expérience, spécialisé dans concevoir, construire et héberger des projets Web.<br/><br/>Originaire du Liban, ma passion précoce pour l'informatique m'a conduit à un baccalauréat en informatique à l'<a href='https://www.balamand.edu.lb' target='_blank' rel='noreferrer'>Université de Balamand</a>. En 2018, j’ai entrepris un voyage sur la côte Est du Canada pour poursuivre ma maîtrise à l'<a href='https://www.smu.ca' target='_blank' rel='noreferrer'>Université Saint Mary’s</a>.<br/><br/>Maintenant je suis basé à Halifax, en Nouvelle-Écosse, où je poursuis mon parcours dans le monde du développement de logiciels, en explorant des solutions innovantes avec <a href='https://redspace.com/' target='_blank' rel='noreferrer'>REDspace</a> et en m'adonnant occasionnellement à des projets parallèles le week-end.<br/><br/>Quand je ne regarde pas un écran, je joue de la musique sur le Oud et je chante parfois."
  },
  "Footer": {
    "copyright": "© Simon Achkar",
    "builtWith": "Construit avec <a href='https://nextjs.org' target='_blank' rel='noreferrer'>Next.js</a> et <a href='https://tailwindcss.com' target='_blank' rel='noreferrer'>Tailwind CSS</a>, déployé avec <a href='https://www.netlify.com' target='_blank' rel='noreferrer'>Netlify</a>. Le texte est défini dans les polices <a href='https://fonts.google.com/specimen/Montserrat' target='_blank' rel='noreferrer'>Montserrat</a> et <a href='https://fonts.google.com/specimen/Rubik' target='_blank' rel='noreferrer'>Rubik</a>.",
    "madeWith": "Réalisé avec"
  }
}
